mkdocs_techdocs_core-1.6.1.dist-info/licenses/LICENSE
techdocs_core/__init__.py
techdocs_core/core.py
techdocs_core/test_core.py
mkdocs_techdocs_core-1.6.1.dist-info/METADATA
mkdocs_techdocs_core-1.6.1.dist-info/WHEEL
mkdocs_techdocs_core-1.6.1.dist-info/entry_points.txt
mkdocs_techdocs_core-1.6.1.dist-info/top_level.txt
mkdocs_techdocs_core-1.6.1.dist-info/RECORD
